pygoslin/__init__.py
pygoslin/data/goslin/FattyAcids.g4
pygoslin/data/goslin/Goslin.g4
pygoslin/data/goslin/GoslinFragments.g4
pygoslin/data/goslin/HMDB.g4
pygoslin/data/goslin/LipidMaps.g4
pygoslin/data/goslin/Shorthand2020.g4
pygoslin/data/goslin/SumFormula.g4
pygoslin/data/goslin/SwissLipids.g4
pygoslin/data/goslin/Systematic.g4
pygoslin/data/goslin/functional-groups.csv
pygoslin/data/goslin/lipid-list.csv
pygoslin/domain/Adduct.py
pygoslin/domain/Cycle.py
pygoslin/domain/Element.py
pygoslin/domain/FattyAcid.py
pygoslin/domain/Fragment.py
pygoslin/domain/FunctionalGroup.py
pygoslin/domain/HeadGroup.py
pygoslin/domain/LipidAdduct.py
pygoslin/domain/LipidCategory.py
pygoslin/domain/LipidClass.py
pygoslin/domain/LipidCompleteStructure.py
pygoslin/domain/LipidExceptions.py
pygoslin/domain/LipidFaBondType.py
pygoslin/domain/LipidFullStructure.py
pygoslin/domain/LipidLevel.py
pygoslin/domain/LipidMolecularSpecies.py
pygoslin/domain/LipidSnPosition.py
pygoslin/domain/LipidSpecies.py
pygoslin/domain/LipidSpeciesInfo.py
pygoslin/domain/LipidStructureDefined.py
pygoslin/domain/__init__.py
pygoslin/parser/BaseParserEventHandler.py
pygoslin/parser/FattyAcidParserEventHandler.py
pygoslin/parser/GoslinParserEventHandler.py
pygoslin/parser/HmdbParserEventHandler.py
pygoslin/parser/LipidBaseParserEventHandler.py
pygoslin/parser/LipidMapsParserEventHandler.py
pygoslin/parser/Parser.py
pygoslin/parser/ParserCommon.py
pygoslin/parser/ShorthandParserEventHandler.py
pygoslin/parser/SumFormulaParserEventHandler.py
pygoslin/parser/SwissLipidsParserEventHandler.py
pygoslin/parser/SystematicParserEventHandler.py
pygoslin/parser/__init__.py
pygoslin/tests/FattyAcids_test.py
pygoslin/tests/Formulas_test.py
pygoslin/tests/Goslin_test.py
pygoslin/tests/Hmdb_test.py
pygoslin/tests/LipidMaps_test.py
pygoslin/tests/Masses_test.py
pygoslin/tests/Parser_test.py
pygoslin/tests/Shorthand_test.py
pygoslin/tests/SwissLipids_test.py
pygoslin/tests/__init__.py
pygoslin-2.1.0.dist-info/LICENSE
pygoslin-2.1.0.dist-info/METADATA
pygoslin-2.1.0.dist-info/WHEEL
pygoslin-2.1.0.dist-info/top_level.txt
pygoslin-2.1.0.dist-info/RECORD
