Metadata-Version: 2.1
Name: pygoslin
Version: 2.1.0
Summary: Python implementation for Goslin
Home-page: https://github.com/lifs-tools/pygoslin
Author: Dominik Kopczynski
Author-email: dominik.kopczynski@univie.ac.at
License: MIT
Classifier: Programming Language :: Python :: 3
Classifier: License :: OSI Approved :: MIT License
Classifier: Operating System :: OS Independent
Requires-Python: >=3.5
License-File: LICENSE
